hypnettorch/__init__.py
hypnettorch/untitled0.py
hypnettorch/data/__init__.py
hypnettorch/data/celeba_data.py
hypnettorch/data/cifar100_data.py
hypnettorch/data/cifar10_data.py
hypnettorch/data/cub_200_2011_data.py
hypnettorch/data/dataset.py
hypnettorch/data/fashion_mnist.py
hypnettorch/data/ilsvrc2012_data.py
hypnettorch/data/large_img_dataset.py
hypnettorch/data/mnist_data.py
hypnettorch/data/sequential_dataset.py
hypnettorch/data/svhn_data.py
hypnettorch/data/udacity_ch2.py
hypnettorch/data/special/__init__.py
hypnettorch/data/special/donuts.py
hypnettorch/data/special/gaussian_mixture_data.py
hypnettorch/data/special/gmm_data.py
hypnettorch/data/special/permuted_mnist.py
hypnettorch/data/special/regression1d_bimodal_data.py
hypnettorch/data/special/regression1d_data.py
hypnettorch/data/special/split_cifar.py
hypnettorch/data/special/split_mnist.py
hypnettorch/data/timeseries/__init__.py
hypnettorch/data/timeseries/audioset_data.py
hypnettorch/data/timeseries/copy_data.py
hypnettorch/data/timeseries/mud_data.py
hypnettorch/data/timeseries/permuted_copy.py
hypnettorch/data/timeseries/preprocess_audioset.py
hypnettorch/data/timeseries/preprocess_mud.py
hypnettorch/data/timeseries/preprocess_smnist.py
hypnettorch/data/timeseries/rnd_rec_teacher.py
hypnettorch/data/timeseries/seq_smnist.py
hypnettorch/data/timeseries/smnist_data.py
hypnettorch/data/timeseries/split_audioset.py
hypnettorch/data/timeseries/split_smnist.py
hypnettorch/data/timeseries/cognitive_tasks/__init__.py
hypnettorch/data/timeseries/cognitive_tasks/cognitive_data.py
hypnettorch/data/timeseries/cognitive_tasks/parameters.py
hypnettorch/data/timeseries/cognitive_tasks/stimulus.py
hypnettorch/hnets/__init__.py
hypnettorch/hnets/chunked_deconv_hnet.py
hypnettorch/hnets/chunked_mlp_hnet.py
hypnettorch/hnets/deconv_hnet.py
hypnettorch/hnets/hnet_container.py
hypnettorch/hnets/hnet_helpers.py
hypnettorch/hnets/hnet_interface.py
hypnettorch/hnets/hnet_perturbation_wrapper.py
hypnettorch-0.0.4.dist-info/LICENSE
hypnettorch-0.0.4.dist-info/METADATA
hypnettorch-0.0.4.dist-info/WHEEL
hypnettorch-0.0.4.dist-info/top_level.txt
hypnettorch-0.0.4.dist-info/RECORD
