Metadata-Version: 2.1
Name: hypnettorch
Version: 0.0.4
Summary: Hypernetwork library for PyTorch
Home-page: https://github.com/chrhenning/hypnettorch
Author: Christian Henning, Maria R. Cervera
Author-email: henningc@ethz.ch
License: UNKNOWN
Project-URL: Bug Tracker, https://github.com/chrhenning/hypnettorch/issues
Platform: UNKNOWN
Classifier: Programming Language :: Python :: 3
Classifier: License :: OSI Approved :: Apache Software License
Classifier: Operating System :: OS Independent
Requires-Python: >=3.6
License-File: LICENSE
